string_palavras_2025-0.1.0.dist-info/licenses/license
string_utils/__init__.py
string_palavras_2025-0.1.0.dist-info/METADATA
string_palavras_2025-0.1.0.dist-info/WHEEL
string_palavras_2025-0.1.0.dist-info/top_level.txt
string_palavras_2025-0.1.0.dist-info/RECORD
