Metadata-Version: 2.4
Name: string-palavras-2025
Version: 0.1.0
Summary: Manipulação de strings
Author-email: Nome <nome@email.com>
License: MIT
Requires-Python: >=3.8
License-File: license
Dynamic: license-file
